MANIFEST.in
README.md
requirements.txt
setup.py
default_rest_framework/__init__.py
default_rest_framework/exceptions.py
default_rest_framework/field.py
default_rest_framework/filters.py
default_rest_framework/generics.py
default_rest_framework/interfaces.py
default_rest_framework/middleware.py
default_rest_framework/mixins.py
default_rest_framework/models.py
default_rest_framework/pagination.py
default_rest_framework/permissions.py
default_rest_framework/response.py
default_rest_framework/serializers.py
default_rest_framework/validator.py
default_rest_framework/views.py
default_rest_framework/viewsets.py
extradrf.egg-info/PKG-INFO
extradrf.egg-info/SOURCES.txt
extradrf.egg-info/dependency_links.txt
extradrf.egg-info/requires.txt
extradrf.egg-info/top_level.txt
extradrf.egg-info/zip-safe
utils/__init__.py
utils/auth.py
utils/check_config.py
utils/connect.py
utils/constants.py
utils/decorators.py
utils/exceptions.py
utils/http_service.py
utils/ik_util.py
utils/json.py
utils/jwt.py
utils/mimes.py
utils/status_code.py
utils/test.py
utils/threads.py
utils/validator.py