Metadata-Version: 2.1
Name: extradrf
Version: 0.0.11
Summary: a framework based on django_rest_framework
Home-page: https://github.com/jxs1211/extradrf
Author: shenxianjie
Author-email: 327411586@qq.com
License: MIT
Platform: all
Classifier: Programming Language :: Python :: 3.7
Classifier: License :: OSI Approved :: MIT License
Classifier: Operating System :: OS Independent
